design.sv
module password_lock(
    input clk,
    input reset,
    input key,
    output reg unlock
);

parameter S0 = 2'b00;
parameter S1 = 2'b01;
parameter S2 = 2'b10;
parameter S3 = 2'b11;

reg [1:0] state;

always @(posedge clk or posedge reset)
begin
    if(reset)
    begin
        state <= S0;
        unlock <= 0;
    end
    else
    begin
        unlock <= 0;

        case(state)

            // First correct key
            S0:
            begin
                if(key)
                    state <= S1;
            end

            // Second correct key
            S1:
            begin
                if(key)
                    state <= S2;
                else
                    state <= S0;
            end

            // Third correct key
            S2:
            begin
                if(key)
                begin
                    state <= S3;
                    unlock <= 1;
                end
                else
                    state <= S0;
            end

            // Door unlocked
            S3:
            begin
                state <= S0;
                unlock <= 0;
            end

            default:
            begin
                state <= S0;
                unlock <= 0;
            end

        endcase
    end
end

endmodule

testbench.sv
`timescale 1ns/1ps

module tb_password_lock;

reg clk;
reg reset;
reg key;

wire unlock;

password_lock uut(
    .clk(clk),
    .reset(reset),
    .key(key),
    .unlock(unlock)
);

// Clock
always #5 clk = ~clk;

initial
begin
    clk = 0;
    reset = 1;
    key = 0;

    $dumpfile("dump.vcd");
    $dumpvars(0, tb_password_lock);

    #10 reset = 0;

    // Correct sequence: 1,1,1
    #10 key = 1;
    #10 key = 1;
    #10 key = 1;

    #10 key = 0;

    // Try again
    #20 key = 1;
    #10 key = 1;
    #10 key = 1;

    #20;

    $finish;
end

initial
begin
    $monitor("Time=%0t State=%b Key=%b Unlock=%b",
             $time,
             uut.state,
             key,
             unlock);
end

endmodule

dump.vcd
$version Generated by VerilatedVcd $end
$timescale 1ps $end
 $scope module tb_password_lock $end
  $var wire 1 # clk $end
  $var wire 1 $ reset $end
  $var wire 1 % key $end
  $var wire 1 & unlock $end
  $scope module uut $end
   $var wire 1 # clk $end
   $var wire 1 $ reset $end
   $var wire 1 % key $end
   $var wire 1 & unlock $end
   $var wire 2 ( S0 [1:0] $end
   $var wire 2 ) S1 [1:0] $end
   $var wire 2 * S2 [1:0] $end
   $var wire 2 + S3 [1:0] $end
   $var wire 2 ' state [1:0] $end
  $upscope $end
 $upscope $end
$enddefinitions $end


#0
0#
1$
0%
0&
b00 '
b00 (
b01 )
b10 *
b11 +
#5000
1#
#10000
0#
0$
#15000
1#
#20000
0#
1%
#25000
1#
b01 '
#30000
0#
#35000
1#
b10 '
#40000
0#
#45000
1#
1&
b11 '
#50000
0#
0%
#55000
1#
0&
b00 '
#60000
0#
#65000
1#
#70000
0#
1%
#75000
1#
b01 '
#80000
0#
#85000
1#
b10 '
#90000
0#
#95000
1#
1&
b11 '
#100000
0#
#105000
1#
0&
b00 '
