design.sv
module vending_machine(
    input clk,
    input reset,
    input coin5,
    input coin10,
    output reg dispense
);

parameter S0  = 2'b00;
parameter S5  = 2'b01;
parameter S10 = 2'b10;

reg [1:0] state;

always @(posedge clk or posedge reset)
begin
    if(reset)
    begin
        state <= S0;
        dispense <= 0;
    end
    else
    begin
        dispense <= 0;

        case(state)

            S0:
            begin
                if(coin5)
                    state <= S5;

                else if(coin10)
                begin
                    state <= S10;
                    dispense <= 1;
                end
            end

            S5:
            begin
                if(coin5)
                begin
                    state <= S10;
                    dispense <= 1;
                end
                else if(coin10)
                begin
                    state <= S10;
                    dispense <= 1;
                end
            end

            S10:
            begin
                state <= S0;
            end

            default:
            begin
                state <= S0;
                dispense <= 0;
            end

        endcase
    end
end

endmodule

testbench.sv
`timescale 1ns/1ps

module tb_vending_machine;

reg clk;
reg reset;
reg coin5;
reg coin10;

wire dispense;

vending_machine uut(
    .clk(clk),
    .reset(reset),
    .coin5(coin5),
    .coin10(coin10),
    .dispense(dispense)
);

// Clock
always #5 clk = ~clk;

initial
begin
    clk = 0;
    reset = 1;
    coin5 = 0;
    coin10 = 0;

    $dumpfile("dump.vcd");
    $dumpvars(0,tb_vending_machine);

    // Reset
    #10 reset = 0;

    // ₹5
    #10 coin5 = 1;
    #10 coin5 = 0;

    // ₹5 -> Dispense
    #10 coin5 = 1;
    #10 coin5 = 0;

    // Wait
    #20;

    // ₹10 Direct
    coin10 = 1;
    #10 coin10 = 0;

    #40;

    $finish;
end

initial
begin
    $monitor("Time=%0t State=%b Coin5=%b Coin10=%b Dispense=%b",
              $time,
              uut.state,
              coin5,
              coin10,
              dispense);
end

endmodule

dump.vcd
$version Generated by VerilatedVcd $end
$timescale 1ps $end
 $scope module tb_vending_machine $end
  $var wire 1 # clk $end
  $var wire 1 $ reset $end
  $var wire 1 % coin5 $end
  $var wire 1 & coin10 $end
  $var wire 1 ' dispense $end
  $scope module uut $end
   $var wire 1 # clk $end
   $var wire 1 $ reset $end
   $var wire 1 % coin5 $end
   $var wire 1 & coin10 $end
   $var wire 1 ' dispense $end
   $var wire 2 ) S0 [1:0] $end
   $var wire 2 * S5 [1:0] $end
   $var wire 2 + S10 [1:0] $end
   $var wire 2 ( state [1:0] $end
  $upscope $end
 $upscope $end
$enddefinitions $end


#0
0#
1$
0%
0&
0'
b00 (
b00 )
b01 *
b10 +
#5000
1#
#10000
0#
0$
#15000
1#
#20000
0#
1%
#25000
1#
b01 (
#30000
0#
0%
#35000
1#
#40000
0#
1%
#45000
1#
1'
b10 (
#50000
0#
0%
#55000
1#
0'
b00 (
#60000
0#
#65000
1#
#70000
0#
1&
#75000
1#
1'
b10 (
#80000
0#
0&
#85000
1#
0'
b00 (
