design.sv
module mealy_fsm(
    input clk,
    input reset,
    input in,
    output reg out
);
reg state;
always @(posedge clk or posedge reset) begin
    if (reset) begin
        state <= 0;
        out <= 0;
    end
    else begin
        case(state)
            0: begin
                if (in) begin
                    state <= 1;
                    out <= 0;
                end
                else begin
                    state <= 0;
                    out <= 0;
                end
            end
            1: begin
                if (in) begin
                    state <= 1;
                    out <= 1;
                end
                else begin
                    state <= 0;
                    out <= 0;
                end
            end
            default: begin
                state <= 0;
                out <= 0;
            end
        endcase
    end
end
endmodule

testbench.sv
`timescale 1ns/1ps
module tb_mealy_fsm;
reg clk = 0;
reg reset = 1;
reg in = 0;
wire out;
mealy_fsm uut(
    .clk(clk),
    .reset(reset),
    .in(in),
    .out(out)
);
always #5 clk = ~clk;
initial begin
    $dumpfile("mealy_fsm.vcd");
    $dumpvars(0, tb_mealy_fsm);
    #10 reset = 0;
    #10 in = 1;
    #10 in = 1;
    #10 in = 0;
    #10 in = 1;
    #10 in = 1;
    #10 in = 0;
    #20;
    $finish;
end
initial begin
    $monitor("Time=%0t Reset=%b In=%b Out=%b",
              $time, reset, in, out);
end
endmodule

mealy_fsm.vcd
$version Generated by VerilatedVcd $end
$timescale 1ps $end
 $scope module tb_mealy_fsm $end
  $var wire 1 # clk $end
  $var wire 1 $ reset $end
  $var wire 1 % in $end
  $var wire 1 & out $end
  $scope module uut $end
   $var wire 1 # clk $end
   $var wire 1 $ reset $end
   $var wire 1 % in $end
   $var wire 1 & out $end
   $var wire 1 ' state $end
  $upscope $end
 $upscope $end
$enddefinitions $end


#0
0#
1$
0%
0&
0'
#5000
1#
#10000
0#
0$
#15000
1#
#20000
0#
1%
#25000
1#
1'
#30000
0#
#35000
1#
1&
#40000
0#
0%
#45000
1#
0&
0'
#50000
0#
1%
#55000
1#
1'
#60000
0#
#65000
1#
1&
#70000
0#
0%
#75000
1#
0&
0'
