design.sv
module moore_fsm(
    input clk,
    input reset,
    output reg [1:0] state
);

parameter S0 = 2'b00,
          S1 = 2'b01,
          S2 = 2'b10;

always @(posedge clk or posedge reset) begin
    if (reset)
        state <= S0;
    else begin
        case(state)
            S0: state <= S1;
            S1: state <= S2;
            S2: state <= S0;
            default: state <= S0;
        endcase
    end
end
endmodule

testbench.sv
`timescale 1ns/1ps
module tb_moore_fsm;
reg clk = 0;
reg reset = 1;
wire [1:0] state;
moore_fsm uut(
    .clk(clk),
    .reset(reset),
    .state(state)
);
always #5 clk = ~clk;
initial begin
    $dumpfile("moore_fsm.vcd");
    $dumpvars(0, tb_moore_fsm);

    #10 reset = 0;
    #60;
    $finish;
end
initial begin
    $monitor("Time=%0t Reset=%b State=%b",
              $time, reset, state);
end
endmodule

moore_fsm.vcd
$version Generated by VerilatedVcd $end
$timescale 1ps $end
 $scope module tb_moore_fsm $end
  $var wire 1 # clk $end
  $var wire 1 $ reset $end
  $var wire 2 % state [1:0] $end
  $scope module uut $end
   $var wire 1 # clk $end
   $var wire 1 $ reset $end
   $var wire 2 % state [1:0] $end
   $var wire 2 & S0 [1:0] $end
   $var wire 2 ' S1 [1:0] $end
   $var wire 2 ( S2 [1:0] $end
  $upscope $end
 $upscope $end
$enddefinitions $end


#0
0#
1$
b00 %
b00 &
b01 '
b10 (
#5000
1#
#10000
0#
0$
#15000
1#
b01 %
#20000
0#
#25000
1#
b10 %
#30000
0#
#35000
1#
b00 %
#40000
0#
#45000
1#
b01 %
#50000
0#
#55000
1#
b10 %
#60000
0#
#65000
1#
b00 %
