design.sv
module sequence_detector(
    input clk,
    input reset,
    input in,
    output reg detected
);
reg [2:0] state;
always @(posedge clk or posedge reset) begin
    if (reset) begin
        state <= 0;
        detected <= 0;
    end
    else begin
        detected <= 0;

        case(state)

            // S0
            0: begin
                state <= (in) ? 1 : 0;
            end

            // S1
            1: begin
                state <= (in) ? 1 : 2;
            end

            // S2
            2: begin
                state <= (in) ? 3 : 0;
            end

            // S3
            3: begin
                if(in) begin
                    detected <= 1;
                    state <= 1;
                end
                else begin
                    state <= 2;
                end
            end

            default: begin
                state <= 0;
                detected <= 0;
            end

        endcase
    end
end

endmodule

testbench.sv
`timescale 1ns/1ps

module tb_sequence_detector;

reg clk = 0;
reg reset = 1;
reg in = 0;

wire detected;

sequence_detector uut(
    .clk(clk),
    .reset(reset),
    .in(in),
    .detected(detected)
);

// Clock Generation
always #5 clk = ~clk;

// Test Sequence
initial begin

    $dumpfile("sequence_detector.vcd");
    $dumpvars(0, tb_sequence_detector);

    #10 reset = 0;

    // Input Sequence: 1011001011

    #10 in = 1;
    #10 in = 0;
    #10 in = 1;
    #10 in = 1;   // Detect 1011

    #10 in = 0;
    #10 in = 0;
    #10 in = 1;
    #10 in = 0;
    #10 in = 1;
    #10 in = 1;   // Detect again

    #20;

    $finish;

end

initial begin
    $monitor("Time=%0t Reset=%b In=%b Detected=%b",
              $time, reset, in, detected);
end

endmodule

sequence_detector.vcd
$version Generated by VerilatedVcd $end
$timescale 1ps $end
 $scope module tb_sequence_detector $end
  $var wire 1 # clk $end
  $var wire 1 $ reset $end
  $var wire 1 % in $end
  $var wire 1 & detected $end
  $scope module uut $end
   $var wire 1 # clk $end
   $var wire 1 $ reset $end
   $var wire 1 % in $end
   $var wire 1 & detected $end
   $var wire 3 ' state [2:0] $end
  $upscope $end
 $upscope $end
$enddefinitions $end


#0
0#
1$
0%
0&
b000 '
#5000
1#
#10000
0#
0$
#15000
1#
#20000
0#
1%
#25000
1#
b001 '
#30000
0#
0%
#35000
1#
b010 '
#40000
0#
1%
#45000
1#
b011 '
#50000
0#
#55000
1#
1&
b001 '
#60000
0#
0%
#65000
1#
0&
b010 '
#70000
0#
#75000
1#
b000 '
#80000
0#
1%
#85000
1#
b001 '
#90000
0#
0%
#95000
1#
b010 '
#100000
0#
1%
#105000
1#
b011 '
#110000
0#
#115000
1#
1&
b001 '
#120000
0#
#125000
1#
0&
