design.sv
module traffic_light(
    input clk,
    input reset,
    output reg [2:0] light
);

parameter RED    = 3'b100,
          YELLOW = 3'b010,
          GREEN  = 3'b001;

reg [1:0] state;

always @(posedge clk or posedge reset) begin
    if (reset) begin
        state <= 2'd0;
        light <= RED;
    end
    else begin
        case(state)

            2'd0: begin
                state <= 2'd1;
                light <= GREEN;
            end

            2'd1: begin
                state <= 2'd2;
                light <= YELLOW;
            end

            2'd2: begin
                state <= 2'd0;
                light <= RED;
            end

            default: begin
                state <= 2'd0;
                light <= RED;
            end

        endcase
    end
end

endmodule

testbench.sv
`timescale 1ns/1ps

module tb_traffic_light;

reg clk = 0;
reg reset = 1;

wire [2:0] light;

traffic_light uut(
    .clk(clk),
    .reset(reset),
    .light(light)
);

always #5 clk = ~clk;

initial begin

    $dumpfile("traffic_light.vcd");
    $dumpvars(0, tb_traffic_light);

    #10 reset = 0;

    #100;

    $finish;

end

initial begin
    $monitor("Time=%0t Reset=%b Light=%b",
              $time, reset, light);
end

endmodule

traffic_light.vcd
$version Generated by VerilatedVcd $end
$timescale 1ps $end
 $scope module tb_traffic_light $end
  $var wire 1 # clk $end
  $var wire 1 $ reset $end
  $var wire 3 % light [2:0] $end
  $scope module uut $end
   $var wire 1 # clk $end
   $var wire 1 $ reset $end
   $var wire 3 % light [2:0] $end
   $var wire 3 ' RED [2:0] $end
   $var wire 3 ( YELLOW [2:0] $end
   $var wire 3 ) GREEN [2:0] $end
   $var wire 2 & state [1:0] $end
  $upscope $end
 $upscope $end
$enddefinitions $end


#0
0#
1$
b000 %
b00 &
b100 '
b010 (
b001 )
#5000
1#
b100 %
#10000
0#
0$
#15000
1#
b001 %
b01 &
#20000
0#
#25000
1#
b010 %
b10 &
#30000
0#
#35000
1#
b100 %
b00 &
#40000
0#
#45000
1#
b001 %
b01 &
#50000
0#
#55000
1#
b010 %
b10 &
#60000
0#
#65000
1#
b100 %
b00 &
#70000
0#
#75000
1#
b001 %
b01 &
#80000
0#
#85000
1#
b010 %
b10 &
#90000
0#
#95000
1#
b100 %
b00 &
#100000
0#
#105000
1#
b001 %
b01 &
